netcdfella/__init__.py
netcdfella/cli/__init__.py
netcdfella/cli/__main__.py
netcdfella/cli/__version__.py
netcdfella/cli/converter.py
netcdfella/cli/server.py
netcdfella/cli/watcher.py
netcdfella/core/__init__.py
netcdfella/core/conversion.py
netcdfella/core/document.py
netcdfella/core/maps.py
netcdfella/core/test_document.py
netcdfella/core/test_netcdf4.nc
netcdfella/qnotify/__init__.py
netcdfella/qnotify/event_processor.py
netcdfella/qnotify/queues.py
netcdfella/qnotify/watcher.py
netcdfella-0.3.4.dist-info/entry_points.txt
netcdfella-0.3.4.dist-info/LICENSE.md
netcdfella-0.3.4.dist-info/WHEEL
netcdfella-0.3.4.dist-info/METADATA
netcdfella-0.3.4.dist-info/RECORD
