Metadata-Version: 2.1
Name: netcdfella
Version: 0.3.4
Summary: Netcdfella is providing multiple ways to convert netcdf filed into other data types such as ASCII, PNG and JPG, and even create graphs.
Home-page: https://nikfot.github.io/netcdfella/
License: GPL-3.0-or-later
Keywords: netcdf,ascii,conversion,png
Author: Nikos Fotiou
Author-email: nik_fot@hotmail.gr
Requires-Python: >=3.10.4,<3.12
Classifier: Development Status :: 3 - Alpha
Classifier: Environment :: Console
Classifier: Framework :: AsyncIO
Classifier: Framework :: Matplotlib
Classifier: License :: OSI Approved :: GNU General Public License v3 (GPLv3)
Classifier: License :: OSI Approved :: GNU General Public License v3 or later (GPLv3+)
Classifier: Programming Language :: Python :: 3
Classifier: Programming Language :: Python :: 3.11
Classifier: Programming Language :: Python :: 3.10
Classifier: Topic :: Scientific/Engineering :: Image Processing
Requires-Dist: Cartopy (==0.21.0)
Requires-Dist: DataShape (==0.5.2)
Requires-Dist: HeapDict (==1.0.1)
Requires-Dist: Jinja2 (==3.0.3)
Requires-Dist: Markdown (==3.4.1)
Requires-Dist: MarkupSafe (==2.1.1)
Requires-Dist: MetPy (==1.3.1)
Requires-Dist: Pillow (==9.2.0)
Requires-Dist: Pint (==0.19.2)
Requires-Dist: PyYAML (==6.0)
Requires-Dist: Shapely (==1.8.4)
Requires-Dist: appdirs (==1.4.4)
Requires-Dist: astroid (==2.12.5)
Requires-Dist: basemap (==1.3.4)
Requires-Dist: basemap-data (==1.3.2)
Requires-Dist: basemap-data-hires (==1.3.2)
Requires-Dist: black (==22.8.0)
Requires-Dist: bleach (==5.0.1)
Requires-Dist: bokeh (==2.4.3)
Requires-Dist: certifi (==2022.9.14)
Requires-Dist: cftime (==1.6.1)
Requires-Dist: charset-normalizer (==2.1.1)
Requires-Dist: click (==8.1.3)
Requires-Dist: cloudpickle (==2.2.0)
Requires-Dist: colorcet (==3.0.0)
Requires-Dist: contourpy (==1.0.5)
Requires-Dist: cycler (==0.11.0)
Requires-Dist: dask (==2022.9.1)
Requires-Dist: datashader (==0.14.2)
Requires-Dist: dill (==0.3.5.1)
Requires-Dist: distributed (==2022.9.1)
Requires-Dist: flake8 (==5.0.4)
Requires-Dist: fonttools (==4.37.2)
Requires-Dist: fsspec (==2022.8.2)
Requires-Dist: holoviews (==1.15.0)
Requires-Dist: hvplot (==0.8.1)
Requires-Dist: idna (==3.4)
Requires-Dist: isort (==5.10.1)
Requires-Dist: kiwisolver (==1.4.4)
Requires-Dist: lazy-object-proxy (==1.7.1)
Requires-Dist: llvmlite (==0.39.1)
Requires-Dist: locket (==1.0.0)
Requires-Dist: matplotlib (==3.5.3)
Requires-Dist: mccabe (==0.7.0)
Requires-Dist: msgpack (==1.0.4)
Requires-Dist: multipledispatch (==0.6.0)
Requires-Dist: mypy-extensions (==0.4.3)
Requires-Dist: ncplot (==0.2.4)
Requires-Dist: netCDF4 (==1.6.1)
Requires-Dist: nose (==1.3.7)
Requires-Dist: numba (==0.56.2)
Requires-Dist: numpy (==1.23.3)
Requires-Dist: packaging (==21.3)
Requires-Dist: pandas (==1.4.4)
Requires-Dist: panel (==0.13.1)
Requires-Dist: param (==1.12.2)
Requires-Dist: partd (==1.3.0)
Requires-Dist: pathspec (==0.10.1)
Requires-Dist: platformdirs (==2.5.2)
Requires-Dist: pooch (==1.6.0)
Requires-Dist: psutil (==5.9.2)
Requires-Dist: pycodestyle (==2.9.1)
Requires-Dist: pyct (==0.4.8)
Requires-Dist: pyflakes (==2.5.0)
Requires-Dist: pyinotify (==0.9.6)
Requires-Dist: pylint (==2.15.0)
Requires-Dist: pyparsing (==3.0.9)
Requires-Dist: pyproj (==3.3.1)
Requires-Dist: pyshp (==2.3.1)
Requires-Dist: python-dateutil (==2.8.2)
Requires-Dist: pytz (==2022.2.1)
Requires-Dist: pyviz-comms (==2.2.1)
Requires-Dist: requests (==2.28.1)
Requires-Dist: scipy (==1.9.1)
Requires-Dist: six (==1.16.0)
Requires-Dist: sortedcontainers (==2.4.0)
Requires-Dist: tblib (==1.7.0)
Requires-Dist: thread6 (==0.2.0)
Requires-Dist: tomli (==2.0.1)
Requires-Dist: tomlkit (==0.11.4)
Requires-Dist: toolz (==0.12.0)
Requires-Dist: tornado (==6.1)
Requires-Dist: tqdm (==4.64.1)
Requires-Dist: traitlets (==5.4.0)
Requires-Dist: typing-extensions (==4.3.0)
Requires-Dist: urllib3 (==1.26.12)
Requires-Dist: webencodings (==0.5.1)
Requires-Dist: wrapt (==1.14.1)
Requires-Dist: xarray (==2022.6.0)
Requires-Dist: zict (==2.2.0)
Project-URL: Repository, https://github.com/nikfot/netcdfella
